{"page": 2, "successes": 9, "failures": 190, "seconds elapsed": 374.52744793891907, "DATA": [["Atlanta Falcons - Pittsburgh Steelers", "bet-at-home", "+110", "-141", "Sunday, 14 Dec 2014, 17:00", "Final result 20:27 (0:6, 7:14, 6:0, 7:7)"], ["Atlanta Falcons - Pittsburgh Steelers", "bet365", "+110", "-132", "Sunday, 14 Dec 2014, 17:00", "Final result 20:27 (0:6, 7:14, 6:0, 7:7)"], ["Atlanta Falcons - Pittsburgh Steelers", "bwin", "+104", "-125", "Sunday, 14 Dec 2014, 17:00", "Final result 20:27 (0:6, 7:14, 6:0, 7:7)"], ["Atlanta Falcons - Pittsburgh Steelers", "Marathonbet", "+118", "-128", "Sunday, 14 Dec 2014, 17:00", "Final result 20:27 (0:6, 7:14, 6:0, 7:7)"], ["Atlanta Falcons - Pittsburgh Steelers", "Pinnacle", "+129", "-143", "Sunday, 14 Dec 2014, 17:00", "Final result 20:27 (0:6, 7:14, 6:0, 7:7)"], ["Atlanta Falcons - Pittsburgh Steelers", "Unibet", "+120", "-143", "Sunday, 14 Dec 2014, 17:00", "Final result 20:27 (0:6, 7:14, 6:0, 7:7)"], ["Atlanta Falcons - Pittsburgh Steelers", "William Hill", "+114", "-135", "Sunday, 14 Dec 2014, 17:00", "Final result 20:27 (0:6, 7:14, 6:0, 7:7)"], ["Atlanta Falcons - Pittsburgh Steelers", null, null, null, "Sunday, 14 Dec 2014, 17:00", "Final result 20:27 (0:6, 7:14, 6:0, 7:7)"], ["Atlanta Falcons - Pittsburgh Steelers", null, null, null, "Sunday, 14 Dec 2014, 17:00", "Final result 20:27 (0:6, 7:14, 6:0, 7:7)"], ["Atlanta Falcons - Pittsburgh Steelers", null, null, null, "Sunday, 14 Dec 2014, 17:00", "Final result 20:27 (0:6, 7:14, 6:0, 7:7)"], ["Atlanta Falcons - Pittsburgh Steelers", null, null, null, "Sunday, 14 Dec 2014, 17:00", "Final result 20:27 (0:6, 7:14, 6:0, 7:7)"], ["Atlanta Falcons - Pittsburgh Steelers", null, null, null, "Sunday, 14 Dec 2014, 17:00", "Final result 20:27 (0:6, 7:14, 6:0, 7:7)"], ["Atlanta Falcons - Pittsburgh Steelers", null, null, null, "Sunday, 14 Dec 2014, 17:00", "Final result 20:27 (0:6, 7:14, 6:0, 7:7)"], ["Atlanta Falcons - Pittsburgh Steelers", null, null, null, "Sunday, 14 Dec 2014, 17:00", "Final result 20:27 (0:6, 7:14, 6:0, 7:7)"], ["Atlanta Falcons - Pittsburgh Steelers", null, null, null, "Sunday, 14 Dec 2014, 17:00", "Final result 20:27 (0:6, 7:14, 6:0, 7:7)"], ["Atlanta Falcons - Pittsburgh Steelers", null, null, null, "Sunday, 14 Dec 2014, 17:00", "Final result 20:27 (0:6, 7:14, 6:0, 7:7)"], ["Atlanta Falcons - Pittsburgh Steelers", null, null, null, "Sunday, 14 Dec 2014, 17:00", "Final result 20:27 (0:6, 7:14, 6:0, 7:7)"], ["Atlanta Falcons - Pittsburgh Steelers", null, null, null, "Sunday, 14 Dec 2014, 17:00", "Final result 20:27 (0:6, 7:14, 6:0, 7:7)"], ["Atlanta Falcons - Pittsburgh Steelers", null, null, null, "Sunday, 14 Dec 2014, 17:00", "Final result 20:27 (0:6, 7:14, 6:0, 7:7)"], ["Atlanta Falcons - Pittsburgh Steelers", null, null, null, "Sunday, 14 Dec 2014, 17:00", "Final result 20:27 (0:6, 7:14, 6:0, 7:7)"], ["Atlanta Falcons - Pittsburgh Steelers", null, null, null, "Sunday, 14 Dec 2014, 17:00", "Final result 20:27 (0:6, 7:14, 6:0, 7:7)"], ["Atlanta Falcons - Pittsburgh Steelers", null, null, null, "Sunday, 14 Dec 2014, 17:00", "Final result 20:27 (0:6, 7:14, 6:0, 7:7)"], ["Atlanta Falcons - Pittsburgh Steelers", null, null, null, "Sunday, 14 Dec 2014, 17:00", "Final result 20:27 (0:6, 7:14, 6:0, 7:7)"], ["Atlanta Falcons - Pittsburgh Steelers", null, null, null, "Sunday, 14 Dec 2014, 17:00", "Final result 20:27 (0:6, 7:14, 6:0, 7:7)"], ["Atlanta Falcons - Pittsburgh Steelers", null, null, null, "Sunday, 14 Dec 2014, 17:00", "Final result 20:27 (0:6, 7:14, 6:0, 7:7)"], ["Atlanta Falcons - Pittsburgh Steelers", null, null, null, "Sunday, 14 Dec 2014, 17:00", "Final result 20:27 (0:6, 7:14, 6:0, 7:7)"], ["Atlanta Falcons - Pittsburgh Steelers", null, null, null, "Sunday, 14 Dec 2014, 17:00", "Final result 20:27 (0:6, 7:14, 6:0, 7:7)"], ["Atlanta Falcons - Pittsburgh Steelers", null, null, null, "Sunday, 14 Dec 2014, 17:00", "Final result 20:27 (0:6, 7:14, 6:0, 7:7)"], ["Atlanta Falcons - Pittsburgh Steelers", null, null, null, "Sunday, 14 Dec 2014, 17:00", "Final result 20:27 (0:6, 7:14, 6:0, 7:7)"], ["Baltimore Ravens - Jacksonville Jaguars", "bet-at-home", "-1250", "+646", "Sunday, 14 Dec 2014, 17:00", "Final result 20:12 (7:6, 3:6, 7:0, 3:0)"], ["Baltimore Ravens - Jacksonville Jaguars", "bet365", "-1000", "+650", "Sunday, 14 Dec 2014, 17:00", "Final result 20:12 (7:6, 3:6, 7:0, 3:0)"], ["Baltimore Ravens - Jacksonville Jaguars", "bwin", "-1000", "+650", "Sunday, 14 Dec 2014, 17:00", "Final result 20:12 (7:6, 3:6, 7:0, 3:0)"], ["Baltimore Ravens - Jacksonville Jaguars", "Marathonbet", "-909", "+730", "Sunday, 14 Dec 2014, 17:00", "Final result 20:12 (7:6, 3:6, 7:0, 3:0)"], ["Baltimore Ravens - Jacksonville Jaguars", "Pinnacle", "-909", "+703", "Sunday, 14 Dec 2014, 17:00", "Final result 20:12 (7:6, 3:6, 7:0, 3:0)"], ["Baltimore Ravens - Jacksonville Jaguars", "Unibet", "-1000", "+650", "Sunday, 14 Dec 2014, 17:00", "Final result 20:12 (7:6, 3:6, 7:0, 3:0)"], ["Baltimore Ravens - Jacksonville Jaguars", "William Hill", "-1000", "+650", "Sunday, 14 Dec 2014, 17:00", "Final result 20:12 (7:6, 3:6, 7:0, 3:0)"], ["Baltimore Ravens - Jacksonville Jaguars", null, null, null, "Sunday, 14 Dec 2014, 17:00", "Final result 20:12 (7:6, 3:6, 7:0, 3:0)"], ["Baltimore Ravens - Jacksonville Jaguars", null, null, null, "Sunday, 14 Dec 2014, 17:00", "Final result 20:12 (7:6, 3:6, 7:0, 3:0)"], ["Baltimore Ravens - Jacksonville Jaguars", null, null, null, "Sunday, 14 Dec 2014, 17:00", "Final result 20:12 (7:6, 3:6, 7:0, 3:0)"], ["Baltimore Ravens - Jacksonville Jaguars", null, null, null, "Sunday, 14 Dec 2014, 17:00", "Final result 20:12 (7:6, 3:6, 7:0, 3:0)"], ["Baltimore Ravens - Jacksonville Jaguars", null, null, null, "Sunday, 14 Dec 2014, 17:00", "Final result 20:12 (7:6, 3:6, 7:0, 3:0)"], ["Baltimore Ravens - Jacksonville Jaguars", null, null, null, "Sunday, 14 Dec 2014, 17:00", "Final result 20:12 (7:6, 3:6, 7:0, 3:0)"], ["Baltimore Ravens - Jacksonville Jaguars", null, null, null, "Sunday, 14 Dec 2014, 17:00", "Final result 20:12 (7:6, 3:6, 7:0, 3:0)"], ["Baltimore Ravens - Jacksonville Jaguars", null, null, null, "Sunday, 14 Dec 2014, 17:00", "Final result 20:12 (7:6, 3:6, 7:0, 3:0)"], ["Baltimore Ravens - Jacksonville Jaguars", null, null, null, "Sunday, 14 Dec 2014, 17:00", "Final result 20:12 (7:6, 3:6, 7:0, 3:0)"], ["Baltimore Ravens - Jacksonville Jaguars", null, null, null, "Sunday, 14 Dec 2014, 17:00", "Final result 20:12 (7:6, 3:6, 7:0, 3:0)"], ["Baltimore Ravens - Jacksonville Jaguars", null, null, null, "Sunday, 14 Dec 2014, 17:00", "Final result 20:12 (7:6, 3:6, 7:0, 3:0)"], ["Baltimore Ravens - Jacksonville Jaguars", null, null, null, "Sunday, 14 Dec 2014, 17:00", "Final result 20:12 (7:6, 3:6, 7:0, 3:0)"], ["Baltimore Ravens - Jacksonville Jaguars", null, null, null, "Sunday, 14 Dec 2014, 17:00", "Final result 20:12 (7:6, 3:6, 7:0, 3:0)"], ["Baltimore Ravens - Jacksonville Jaguars", null, null, null, "Sunday, 14 Dec 2014, 17:00", "Final result 20:12 (7:6, 3:6, 7:0, 3:0)"], ["Baltimore Ravens - Jacksonville Jaguars", null, null, null, "Sunday, 14 Dec 2014, 17:00", "Final result 20:12 (7:6, 3:6, 7:0, 3:0)"], ["Baltimore Ravens - Jacksonville Jaguars", null, null, null, "Sunday, 14 Dec 2014, 17:00", "Final result 20:12 (7:6, 3:6, 7:0, 3:0)"], ["Baltimore Ravens - Jacksonville Jaguars", null, null, null, "Sunday, 14 Dec 2014, 17:00", "Final result 20:12 (7:6, 3:6, 7:0, 3:0)"], ["Baltimore Ravens - Jacksonville Jaguars", null, null, null, "Sunday, 14 Dec 2014, 17:00", "Final result 20:12 (7:6, 3:6, 7:0, 3:0)"], ["Baltimore Ravens - Jacksonville Jaguars", null, null, null, "Sunday, 14 Dec 2014, 17:00", "Final result 20:12 (7:6, 3:6, 7:0, 3:0)"], ["Baltimore Ravens - Jacksonville Jaguars", null, null, null, "Sunday, 14 Dec 2014, 17:00", "Final result 20:12 (7:6, 3:6, 7:0, 3:0)"], ["Baltimore Ravens - Jacksonville Jaguars", null, null, null, "Sunday, 14 Dec 2014, 17:00", "Final result 20:12 (7:6, 3:6, 7:0, 3:0)"], ["Baltimore Ravens - Jacksonville Jaguars", null, null, null, "Sunday, 14 Dec 2014, 17:00", "Final result 20:12 (7:6, 3:6, 7:0, 3:0)"], ["Buffalo Bills - Green Bay Packers", "bet-at-home", "+189", "-250", "Sunday, 14 Dec 2014, 17:00", "Final result 21:13 (7:3, 3:7, 6:0, 5:3)"], ["Buffalo Bills - Green Bay Packers", "bet365", "+185", "-227", "Sunday, 14 Dec 2014, 17:00", "Final result 21:13 (7:3, 3:7, 6:0, 5:3)"], ["Buffalo Bills - Green Bay Packers", "bwin", "+190", "-233", "Sunday, 14 Dec 2014, 17:00", "Final result 21:13 (7:3, 3:7, 6:0, 5:3)"], ["Buffalo Bills - Green Bay Packers", "Marathonbet", "+204", "-227", "Sunday, 14 Dec 2014, 17:00", "Final result 21:13 (7:3, 3:7, 6:0, 5:3)"], ["Buffalo Bills - Green Bay Packers", "Pinnacle", "+195", "-217", "Sunday, 14 Dec 2014, 17:00", "Final result 21:13 (7:3, 3:7, 6:0, 5:3)"], ["Buffalo Bills - Green Bay Packers", "Unibet", "+190", "-233", "Sunday, 14 Dec 2014, 17:00", "Final result 21:13 (7:3, 3:7, 6:0, 5:3)"], ["Buffalo Bills - Green Bay Packers", "William Hill", "+190", "-233", "Sunday, 14 Dec 2014, 17:00", "Final result 21:13 (7:3, 3:7, 6:0, 5:3)"], ["Buffalo Bills - Green Bay Packers", null, null, null, "Sunday, 14 Dec 2014, 17:00", "Final result 21:13 (7:3, 3:7, 6:0, 5:3)"], ["Buffalo Bills - Green Bay Packers", null, null, null, "Sunday, 14 Dec 2014, 17:00", "Final result 21:13 (7:3, 3:7, 6:0, 5:3)"], ["Buffalo Bills - Green Bay Packers", null, null, null, "Sunday, 14 Dec 2014, 17:00", "Final result 21:13 (7:3, 3:7, 6:0, 5:3)"], ["Buffalo Bills - Green Bay Packers", null, null, null, "Sunday, 14 Dec 2014, 17:00", "Final result 21:13 (7:3, 3:7, 6:0, 5:3)"], ["Buffalo Bills - Green Bay Packers", null, null, null, "Sunday, 14 Dec 2014, 17:00", "Final result 21:13 (7:3, 3:7, 6:0, 5:3)"], ["Buffalo Bills - Green Bay Packers", null, null, null, "Sunday, 14 Dec 2014, 17:00", "Final result 21:13 (7:3, 3:7, 6:0, 5:3)"], ["Buffalo Bills - Green Bay Packers", null, null, null, "Sunday, 14 Dec 2014, 17:00", "Final result 21:13 (7:3, 3:7, 6:0, 5:3)"], ["Buffalo Bills - Green Bay Packers", null, null, null, "Sunday, 14 Dec 2014, 17:00", "Final result 21:13 (7:3, 3:7, 6:0, 5:3)"], ["Buffalo Bills - Green Bay Packers", null, null, null, "Sunday, 14 Dec 2014, 17:00", "Final result 21:13 (7:3, 3:7, 6:0, 5:3)"], ["Buffalo Bills - Green Bay Packers", null, null, null, "Sunday, 14 Dec 2014, 17:00", "Final result 21:13 (7:3, 3:7, 6:0, 5:3)"], ["Buffalo Bills - Green Bay Packers", null, null, null, "Sunday, 14 Dec 2014, 17:00", "Final result 21:13 (7:3, 3:7, 6:0, 5:3)"], ["Buffalo Bills - Green Bay Packers", null, null, null, "Sunday, 14 Dec 2014, 17:00", "Final result 21:13 (7:3, 3:7, 6:0, 5:3)"], ["Buffalo Bills - Green Bay Packers", null, null, null, "Sunday, 14 Dec 2014, 17:00", "Final result 21:13 (7:3, 3:7, 6:0, 5:3)"], ["Buffalo Bills - Green Bay Packers", null, null, null, "Sunday, 14 Dec 2014, 17:00", "Final result 21:13 (7:3, 3:7, 6:0, 5:3)"], ["Buffalo Bills - Green Bay Packers", null, null, null, "Sunday, 14 Dec 2014, 17:00", "Final result 21:13 (7:3, 3:7, 6:0, 5:3)"], ["Buffalo Bills - Green Bay Packers", null, null, null, "Sunday, 14 Dec 2014, 17:00", "Final result 21:13 (7:3, 3:7, 6:0, 5:3)"], ["Buffalo Bills - Green Bay Packers", null, null, null, "Sunday, 14 Dec 2014, 17:00", "Final result 21:13 (7:3, 3:7, 6:0, 5:3)"], ["Buffalo Bills - Green Bay Packers", null, null, null, "Sunday, 14 Dec 2014, 17:00", "Final result 21:13 (7:3, 3:7, 6:0, 5:3)"], ["Buffalo Bills - Green Bay Packers", null, null, null, "Sunday, 14 Dec 2014, 17:00", "Final result 21:13 (7:3, 3:7, 6:0, 5:3)"], ["Buffalo Bills - Green Bay Packers", null, null, null, "Sunday, 14 Dec 2014, 17:00", "Final result 21:13 (7:3, 3:7, 6:0, 5:3)"], ["Buffalo Bills - Green Bay Packers", null, null, null, "Sunday, 14 Dec 2014, 17:00", "Final result 21:13 (7:3, 3:7, 6:0, 5:3)"], ["Buffalo Bills - Green Bay Packers", null, null, null, "Sunday, 14 Dec 2014, 17:00", "Final result 21:13 (7:3, 3:7, 6:0, 5:3)"], ["Carolina Panthers - Tampa Bay Buccaneers", "bet-at-home", "-250", "+189", "Sunday, 14 Dec 2014, 17:00", "Final result 19:17 (6:7, 3:3, 7:0, 3:7)"], ["Carolina Panthers - Tampa Bay Buccaneers", "bet365", "-250", "+204", "Sunday, 14 Dec 2014, 17:00", "Final result 19:17 (6:7, 3:3, 7:0, 3:7)"], ["Carolina Panthers - Tampa Bay Buccaneers", "bwin", "-250", "+200", "Sunday, 14 Dec 2014, 17:00", "Final result 19:17 (6:7, 3:3, 7:0, 3:7)"], ["Carolina Panthers - Tampa Bay Buccaneers", "Marathonbet", "-227", "+204", "Sunday, 14 Dec 2014, 17:00", "Final result 19:17 (6:7, 3:3, 7:0, 3:7)"], ["Carolina Panthers - Tampa Bay Buccaneers", "Pinnacle", "-172", "+156", "Sunday, 14 Dec 2014, 17:00", "Final result 19:17 (6:7, 3:3, 7:0, 3:7)"], ["Carolina Panthers - Tampa Bay Buccaneers", "Unibet", "-175", "+147", "Sunday, 14 Dec 2014, 17:00", "Final result 19:17 (6:7, 3:3, 7:0, 3:7)"], ["Carolina Panthers - Tampa Bay Buccaneers", "William Hill", "-175", "+154", "Sunday, 14 Dec 2014, 17:00", "Final result 19:17 (6:7, 3:3, 7:0, 3:7)"], ["Carolina Panthers - Tampa Bay Buccaneers", null, null, null, "Sunday, 14 Dec 2014, 17:00", "Final result 19:17 (6:7, 3:3, 7:0, 3:7)"], ["Carolina Panthers - Tampa Bay Buccaneers", null, null, null, "Sunday, 14 Dec 2014, 17:00", "Final result 19:17 (6:7, 3:3, 7:0, 3:7)"], ["Carolina Panthers - Tampa Bay Buccaneers", null, null, null, "Sunday, 14 Dec 2014, 17:00", "Final result 19:17 (6:7, 3:3, 7:0, 3:7)"], ["Carolina Panthers - Tampa Bay Buccaneers", null, null, null, "Sunday, 14 Dec 2014, 17:00", "Final result 19:17 (6:7, 3:3, 7:0, 3:7)"], ["Carolina Panthers - Tampa Bay Buccaneers", null, null, null, "Sunday, 14 Dec 2014, 17:00", "Final result 19:17 (6:7, 3:3, 7:0, 3:7)"], ["Carolina Panthers - Tampa Bay Buccaneers", null, null, null, "Sunday, 14 Dec 2014, 17:00", "Final result 19:17 (6:7, 3:3, 7:0, 3:7)"], ["Carolina Panthers - Tampa Bay Buccaneers", null, null, null, "Sunday, 14 Dec 2014, 17:00", "Final result 19:17 (6:7, 3:3, 7:0, 3:7)"], ["Carolina Panthers - Tampa Bay Buccaneers", null, null, null, "Sunday, 14 Dec 2014, 17:00", "Final result 19:17 (6:7, 3:3, 7:0, 3:7)"], ["Carolina Panthers - Tampa Bay Buccaneers", null, null, null, "Sunday, 14 Dec 2014, 17:00", "Final result 19:17 (6:7, 3:3, 7:0, 3:7)"], ["Carolina Panthers - Tampa Bay Buccaneers", null, null, null, "Sunday, 14 Dec 2014, 17:00", "Final result 19:17 (6:7, 3:3, 7:0, 3:7)"], ["Carolina Panthers - Tampa Bay Buccaneers", null, null, null, "Sunday, 14 Dec 2014, 17:00", "Final result 19:17 (6:7, 3:3, 7:0, 3:7)"], ["Carolina Panthers - Tampa Bay Buccaneers", null, null, null, "Sunday, 14 Dec 2014, 17:00", "Final result 19:17 (6:7, 3:3, 7:0, 3:7)"], ["Carolina Panthers - Tampa Bay Buccaneers", null, null, null, "Sunday, 14 Dec 2014, 17:00", "Final result 19:17 (6:7, 3:3, 7:0, 3:7)"], ["Carolina Panthers - Tampa Bay Buccaneers", null, null, null, "Sunday, 14 Dec 2014, 17:00", "Final result 19:17 (6:7, 3:3, 7:0, 3:7)"], ["Carolina Panthers - Tampa Bay Buccaneers", null, null, null, "Sunday, 14 Dec 2014, 17:00", "Final result 19:17 (6:7, 3:3, 7:0, 3:7)"], ["Carolina Panthers - Tampa Bay Buccaneers", null, null, null, "Sunday, 14 Dec 2014, 17:00", "Final result 19:17 (6:7, 3:3, 7:0, 3:7)"], ["Carolina Panthers - Tampa Bay Buccaneers", null, null, null, "Sunday, 14 Dec 2014, 17:00", "Final result 19:17 (6:7, 3:3, 7:0, 3:7)"], ["Carolina Panthers - Tampa Bay Buccaneers", null, null, null, "Sunday, 14 Dec 2014, 17:00", "Final result 19:17 (6:7, 3:3, 7:0, 3:7)"], ["Carolina Panthers - Tampa Bay Buccaneers", null, null, null, "Sunday, 14 Dec 2014, 17:00", "Final result 19:17 (6:7, 3:3, 7:0, 3:7)"], ["Carolina Panthers - Tampa Bay Buccaneers", null, null, null, "Sunday, 14 Dec 2014, 17:00", "Final result 19:17 (6:7, 3:3, 7:0, 3:7)"], ["Carolina Panthers - Tampa Bay Buccaneers", null, null, null, "Sunday, 14 Dec 2014, 17:00", "Final result 19:17 (6:7, 3:3, 7:0, 3:7)"], ["Carolina Panthers - Tampa Bay Buccaneers", null, null, null, "Sunday, 14 Dec 2014, 17:00", "Final result 19:17 (6:7, 3:3, 7:0, 3:7)"], ["Cleveland Browns - Cincinnati Bengals", "bet-at-home", "-105", "-120", "Sunday, 14 Dec 2014, 17:00", "Final result 0:30 (0:10, 0:10, 0:3, 0:7)"], ["Cleveland Browns - Cincinnati Bengals", "bet365", "-116", "-105", "Sunday, 14 Dec 2014, 17:00", "Final result 0:30 (0:10, 0:10, 0:3, 0:7)"], ["Cleveland Browns - Cincinnati Bengals", "bwin", "+104", "-125", "Sunday, 14 Dec 2014, 17:00", "Final result 0:30 (0:10, 0:10, 0:3, 0:7)"], ["Cleveland Browns - Cincinnati Bengals", "Marathonbet", "+108", "-118", "Sunday, 14 Dec 2014, 17:00", "Final result 0:30 (0:10, 0:10, 0:3, 0:7)"], ["Cleveland Browns - Cincinnati Bengals", "Pinnacle", "-114", "+102", "Sunday, 14 Dec 2014, 17:00", "Final result 0:30 (0:10, 0:10, 0:3, 0:7)"], ["Cleveland Browns - Cincinnati Bengals", "Unibet", "-109", "-109", "Sunday, 14 Dec 2014, 17:00", "Final result 0:30 (0:10, 0:10, 0:3, 0:7)"], ["Cleveland Browns - Cincinnati Bengals", "William Hill", "-120", "+100", "Sunday, 14 Dec 2014, 17:00", "Final result 0:30 (0:10, 0:10, 0:3, 0:7)"], ["Cleveland Browns - Cincinnati Bengals", null, null, null, "Sunday, 14 Dec 2014, 17:00", "Final result 0:30 (0:10, 0:10, 0:3, 0:7)"], ["Cleveland Browns - Cincinnati Bengals", null, null, null, "Sunday, 14 Dec 2014, 17:00", "Final result 0:30 (0:10, 0:10, 0:3, 0:7)"], ["Cleveland Browns - Cincinnati Bengals", null, null, null, "Sunday, 14 Dec 2014, 17:00", "Final result 0:30 (0:10, 0:10, 0:3, 0:7)"], ["Cleveland Browns - Cincinnati Bengals", null, null, null, "Sunday, 14 Dec 2014, 17:00", "Final result 0:30 (0:10, 0:10, 0:3, 0:7)"], ["Cleveland Browns - Cincinnati Bengals", null, null, null, "Sunday, 14 Dec 2014, 17:00", "Final result 0:30 (0:10, 0:10, 0:3, 0:7)"], ["Cleveland Browns - Cincinnati Bengals", null, null, null, "Sunday, 14 Dec 2014, 17:00", "Final result 0:30 (0:10, 0:10, 0:3, 0:7)"], ["Cleveland Browns - Cincinnati Bengals", null, null, null, "Sunday, 14 Dec 2014, 17:00", "Final result 0:30 (0:10, 0:10, 0:3, 0:7)"], ["Cleveland Browns - Cincinnati Bengals", null, null, null, "Sunday, 14 Dec 2014, 17:00", "Final result 0:30 (0:10, 0:10, 0:3, 0:7)"], ["Cleveland Browns - Cincinnati Bengals", null, null, null, "Sunday, 14 Dec 2014, 17:00", "Final result 0:30 (0:10, 0:10, 0:3, 0:7)"], ["Cleveland Browns - Cincinnati Bengals", null, null, null, "Sunday, 14 Dec 2014, 17:00", "Final result 0:30 (0:10, 0:10, 0:3, 0:7)"], ["Cleveland Browns - Cincinnati Bengals", null, null, null, "Sunday, 14 Dec 2014, 17:00", "Final result 0:30 (0:10, 0:10, 0:3, 0:7)"], ["Cleveland Browns - Cincinnati Bengals", null, null, null, "Sunday, 14 Dec 2014, 17:00", "Final result 0:30 (0:10, 0:10, 0:3, 0:7)"], ["Cleveland Browns - Cincinnati Bengals", null, null, null, "Sunday, 14 Dec 2014, 17:00", "Final result 0:30 (0:10, 0:10, 0:3, 0:7)"], ["Cleveland Browns - Cincinnati Bengals", null, null, null, "Sunday, 14 Dec 2014, 17:00", "Final result 0:30 (0:10, 0:10, 0:3, 0:7)"], ["Cleveland Browns - Cincinnati Bengals", null, null, null, "Sunday, 14 Dec 2014, 17:00", "Final result 0:30 (0:10, 0:10, 0:3, 0:7)"], ["Cleveland Browns - Cincinnati Bengals", null, null, null, "Sunday, 14 Dec 2014, 17:00", "Final result 0:30 (0:10, 0:10, 0:3, 0:7)"], ["Cleveland Browns - Cincinnati Bengals", null, null, null, "Sunday, 14 Dec 2014, 17:00", "Final result 0:30 (0:10, 0:10, 0:3, 0:7)"], ["Cleveland Browns - Cincinnati Bengals", null, null, null, "Sunday, 14 Dec 2014, 17:00", "Final result 0:30 (0:10, 0:10, 0:3, 0:7)"], ["Cleveland Browns - Cincinnati Bengals", null, null, null, "Sunday, 14 Dec 2014, 17:00", "Final result 0:30 (0:10, 0:10, 0:3, 0:7)"], ["Cleveland Browns - Cincinnati Bengals", null, null, null, "Sunday, 14 Dec 2014, 17:00", "Final result 0:30 (0:10, 0:10, 0:3, 0:7)"], ["Cleveland Browns - Cincinnati Bengals", null, null, null, "Sunday, 14 Dec 2014, 17:00", "Final result 0:30 (0:10, 0:10, 0:3, 0:7)"], ["Cleveland Browns - Cincinnati Bengals", null, null, null, "Sunday, 14 Dec 2014, 17:00", "Final result 0:30 (0:10, 0:10, 0:3, 0:7)"], ["Indianapolis Colts - Houston Texans", "bet-at-home", "-294", "+220", "Sunday, 14 Dec 2014, 17:00", "Final result 17:10 (0:7, 14:0, 0:0, 3:3)"], ["Indianapolis Colts - Houston Texans", "bet365", "-294", "+235", "Sunday, 14 Dec 2014, 17:00", "Final result 17:10 (0:7, 14:0, 0:0, 3:3)"], ["Indianapolis Colts - Houston Texans", "bwin", "-303", "+240", "Sunday, 14 Dec 2014, 17:00", "Final result 17:10 (0:7, 14:0, 0:0, 3:3)"], ["Indianapolis Colts - Houston Texans", "Marathonbet", "-278", "+250", "Sunday, 14 Dec 2014, 17:00", "Final result 17:10 (0:7, 14:0, 0:0, 3:3)"], ["Indianapolis Colts - Houston Texans", "Pinnacle", "-278", "+248", "Sunday, 14 Dec 2014, 17:00", "Final result 17:10 (0:7, 14:0, 0:0, 3:3)"], ["Indianapolis Colts - Houston Texans", "Unibet", "-294", "+240", "Sunday, 14 Dec 2014, 17:00", "Final result 17:10 (0:7, 14:0, 0:0, 3:3)"], ["Indianapolis Colts - Houston Texans", "William Hill", "-303", "+250", "Sunday, 14 Dec 2014, 17:00", "Final result 17:10 (0:7, 14:0, 0:0, 3:3)"], ["Indianapolis Colts - Houston Texans", null, null, null, "Sunday, 14 Dec 2014, 17:00", "Final result 17:10 (0:7, 14:0, 0:0, 3:3)"], ["Indianapolis Colts - Houston Texans", null, null, null, "Sunday, 14 Dec 2014, 17:00", "Final result 17:10 (0:7, 14:0, 0:0, 3:3)"], ["Indianapolis Colts - Houston Texans", null, null, null, "Sunday, 14 Dec 2014, 17:00", "Final result 17:10 (0:7, 14:0, 0:0, 3:3)"], ["Indianapolis Colts - Houston Texans", null, null, null, "Sunday, 14 Dec 2014, 17:00", "Final result 17:10 (0:7, 14:0, 0:0, 3:3)"], ["Indianapolis Colts - Houston Texans", null, null, null, "Sunday, 14 Dec 2014, 17:00", "Final result 17:10 (0:7, 14:0, 0:0, 3:3)"], ["Indianapolis Colts - Houston Texans", null, null, null, "Sunday, 14 Dec 2014, 17:00", "Final result 17:10 (0:7, 14:0, 0:0, 3:3)"], ["Indianapolis Colts - Houston Texans", null, null, null, "Sunday, 14 Dec 2014, 17:00", "Final result 17:10 (0:7, 14:0, 0:0, 3:3)"], ["Indianapolis Colts - Houston Texans", null, null, null, "Sunday, 14 Dec 2014, 17:00", "Final result 17:10 (0:7, 14:0, 0:0, 3:3)"], ["Indianapolis Colts - Houston Texans", null, null, null, "Sunday, 14 Dec 2014, 17:00", "Final result 17:10 (0:7, 14:0, 0:0, 3:3)"], ["Indianapolis Colts - Houston Texans", null, null, null, "Sunday, 14 Dec 2014, 17:00", "Final result 17:10 (0:7, 14:0, 0:0, 3:3)"], ["Indianapolis Colts - Houston Texans", null, null, null, "Sunday, 14 Dec 2014, 17:00", "Final result 17:10 (0:7, 14:0, 0:0, 3:3)"], ["Indianapolis Colts - Houston Texans", null, null, null, "Sunday, 14 Dec 2014, 17:00", "Final result 17:10 (0:7, 14:0, 0:0, 3:3)"], ["Indianapolis Colts - Houston Texans", null, null, null, "Sunday, 14 Dec 2014, 17:00", "Final result 17:10 (0:7, 14:0, 0:0, 3:3)"], ["Indianapolis Colts - Houston Texans", null, null, null, "Sunday, 14 Dec 2014, 17:00", "Final result 17:10 (0:7, 14:0, 0:0, 3:3)"], ["Indianapolis Colts - Houston Texans", null, null, null, "Sunday, 14 Dec 2014, 17:00", "Final result 17:10 (0:7, 14:0, 0:0, 3:3)"], ["Indianapolis Colts - Houston Texans", null, null, null, "Sunday, 14 Dec 2014, 17:00", "Final result 17:10 (0:7, 14:0, 0:0, 3:3)"], ["Indianapolis Colts - Houston Texans", null, null, null, "Sunday, 14 Dec 2014, 17:00", "Final result 17:10 (0:7, 14:0, 0:0, 3:3)"], ["Indianapolis Colts - Houston Texans", null, null, null, "Sunday, 14 Dec 2014, 17:00", "Final result 17:10 (0:7, 14:0, 0:0, 3:3)"], ["Indianapolis Colts - Houston Texans", null, null, null, "Sunday, 14 Dec 2014, 17:00", "Final result 17:10 (0:7, 14:0, 0:0, 3:3)"], ["Indianapolis Colts - Houston Texans", null, null, null, "Sunday, 14 Dec 2014, 17:00", "Final result 17:10 (0:7, 14:0, 0:0, 3:3)"], ["Indianapolis Colts - Houston Texans", null, null, null, "Sunday, 14 Dec 2014, 17:00", "Final result 17:10 (0:7, 14:0, 0:0, 3:3)"], ["Indianapolis Colts - Houston Texans", null, null, null, "Sunday, 14 Dec 2014, 17:00", "Final result 17:10 (0:7, 14:0, 0:0, 3:3)"], ["Kansas City Chiefs - Las Vegas Raiders", "bet-at-home", "-667", "+423", "Sunday, 14 Dec 2014, 17:00", "Final result 31:13 (7:0, 3:3, 21:3, 0:7)"], ["Kansas City Chiefs - Las Vegas Raiders", "bet365", "-625", "+450", "Sunday, 14 Dec 2014, 17:00", "Final result 31:13 (7:0, 3:3, 21:3, 0:7)"], ["Kansas City Chiefs - Las Vegas Raiders", "bwin", "-625", "+450", "Sunday, 14 Dec 2014, 17:00", "Final result 31:13 (7:0, 3:3, 21:3, 0:7)"], ["Kansas City Chiefs - Las Vegas Raiders", "Marathonbet", "-526", "+459", "Sunday, 14 Dec 2014, 17:00", "Final result 31:13 (7:0, 3:3, 21:3, 0:7)"], ["Kansas City Chiefs - Las Vegas Raiders", "Pinnacle", "-556", "+468", "Sunday, 14 Dec 2014, 17:00", "Final result 31:13 (7:0, 3:3, 21:3, 0:7)"], ["Kansas City Chiefs - Las Vegas Raiders", "Unibet", "-625", "+450", "Sunday, 14 Dec 2014, 17:00", "Final result 31:13 (7:0, 3:3, 21:3, 0:7)"], ["Kansas City Chiefs - Las Vegas Raiders", "William Hill", "-588", "+400", "Sunday, 14 Dec 2014, 17:00", "Final result 31:13 (7:0, 3:3, 21:3, 0:7)"], ["Kansas City Chiefs - Las Vegas Raiders", null, null, null, "Sunday, 14 Dec 2014, 17:00", "Final result 31:13 (7:0, 3:3, 21:3, 0:7)"], ["Kansas City Chiefs - Las Vegas Raiders", null, null, null, "Sunday, 14 Dec 2014, 17:00", "Final result 31:13 (7:0, 3:3, 21:3, 0:7)"], ["Kansas City Chiefs - Las Vegas Raiders", null, null, null, "Sunday, 14 Dec 2014, 17:00", "Final result 31:13 (7:0, 3:3, 21:3, 0:7)"], ["Kansas City Chiefs - Las Vegas Raiders", null, null, null, "Sunday, 14 Dec 2014, 17:00", "Final result 31:13 (7:0, 3:3, 21:3, 0:7)"], ["Kansas City Chiefs - Las Vegas Raiders", null, null, null, "Sunday, 14 Dec 2014, 17:00", "Final result 31:13 (7:0, 3:3, 21:3, 0:7)"], ["Kansas City Chiefs - Las Vegas Raiders", null, null, null, "Sunday, 14 Dec 2014, 17:00", "Final result 31:13 (7:0, 3:3, 21:3, 0:7)"], ["Kansas City Chiefs - Las Vegas Raiders", null, null, null, "Sunday, 14 Dec 2014, 17:00", "Final result 31:13 (7:0, 3:3, 21:3, 0:7)"], ["Kansas City Chiefs - Las Vegas Raiders", null, null, null, "Sunday, 14 Dec 2014, 17:00", "Final result 31:13 (7:0, 3:3, 21:3, 0:7)"], ["Kansas City Chiefs - Las Vegas Raiders", null, null, null, "Sunday, 14 Dec 2014, 17:00", "Final result 31:13 (7:0, 3:3, 21:3, 0:7)"], ["Kansas City Chiefs - Las Vegas Raiders", null, null, null, "Sunday, 14 Dec 2014, 17:00", "Final result 31:13 (7:0, 3:3, 21:3, 0:7)"], ["Kansas City Chiefs - Las Vegas Raiders", null, null, null, "Sunday, 14 Dec 2014, 17:00", "Final result 31:13 (7:0, 3:3, 21:3, 0:7)"], ["Kansas City Chiefs - Las Vegas Raiders", null, null, null, "Sunday, 14 Dec 2014, 17:00", "Final result 31:13 (7:0, 3:3, 21:3, 0:7)"], ["Kansas City Chiefs - Las Vegas Raiders", null, null, null, "Sunday, 14 Dec 2014, 17:00", "Final result 31:13 (7:0, 3:3, 21:3, 0:7)"], ["Kansas City Chiefs - Las Vegas Raiders", null, null, null, "Sunday, 14 Dec 2014, 17:00", "Final result 31:13 (7:0, 3:3, 21:3, 0:7)"], ["Kansas City Chiefs - Las Vegas Raiders", null, null, null, "Sunday, 14 Dec 2014, 17:00", "Final result 31:13 (7:0, 3:3, 21:3, 0:7)"], ["Kansas City Chiefs - Las Vegas Raiders", null, null, null, "Sunday, 14 Dec 2014, 17:00", "Final result 31:13 (7:0, 3:3, 21:3, 0:7)"], ["Kansas City Chiefs - Las Vegas Raiders", null, null, null, "Sunday, 14 Dec 2014, 17:00", "Final result 31:13 (7:0, 3:3, 21:3, 0:7)"], ["Kansas City Chiefs - Las Vegas Raiders", null, null, null, "Sunday, 14 Dec 2014, 17:00", "Final result 31:13 (7:0, 3:3, 21:3, 0:7)"], ["Kansas City Chiefs - Las Vegas Raiders", null, null, null, "Sunday, 14 Dec 2014, 17:00", "Final result 31:13 (7:0, 3:3, 21:3, 0:7)"], ["Kansas City Chiefs - Las Vegas Raiders", null, null, null, "Sunday, 14 Dec 2014, 17:00", "Final result 31:13 (7:0, 3:3, 21:3, 0:7)"], ["Kansas City Chiefs - Las Vegas Raiders", null, null, null, "Sunday, 14 Dec 2014, 17:00", "Final result 31:13 (7:0, 3:3, 21:3, 0:7)"], ["Kansas City Chiefs - Las Vegas Raiders", null, null, null, "Sunday, 14 Dec 2014, 17:00", "Final result 31:13 (7:0, 3:3, 21:3, 0:7)"], ["New England Patriots - Miami Dolphins", "bet-at-home", "-417", "+297", "Sunday, 14 Dec 2014, 17:00", "Final result 41:13 (7:3, 7:10, 24:0, 3:0)"], ["New England Patriots - Miami Dolphins", "bet365", "-400", "+309", "Sunday, 14 Dec 2014, 17:00", "Final result 41:13 (7:3, 7:10, 24:0, 3:0)"], ["New England Patriots - Miami Dolphins", "bwin", "-400", "+309", "Sunday, 14 Dec 2014, 17:00", "Final result 41:13 (7:3, 7:10, 24:0, 3:0)"], ["New England Patriots - Miami Dolphins", "Marathonbet", "-385", "+340", "Sunday, 14 Dec 2014, 17:00", "Final result 41:13 (7:3, 7:10, 24:0, 3:0)"], ["New England Patriots - Miami Dolphins", "Pinnacle", "-345", "+301", "Sunday, 14 Dec 2014, 17:00", "Final result 41:13 (7:3, 7:10, 24:0, 3:0)"], ["New England Patriots - Miami Dolphins", "Unibet", "-400", "+315", "Sunday, 14 Dec 2014, 17:00", "Final result 41:13 (7:3, 7:10, 24:0, 3:0)"], ["New England Patriots - Miami Dolphins", "William Hill", "-385", "+290", "Sunday, 14 Dec 2014, 17:00", "Final result 41:13 (7:3, 7:10, 24:0, 3:0)"], ["New England Patriots - Miami Dolphins", null, null, null, "Sunday, 14 Dec 2014, 17:00", "Final result 41:13 (7:3, 7:10, 24:0, 3:0)"], ["New England Patriots - Miami Dolphins", null, null, null, "Sunday, 14 Dec 2014, 17:00", "Final result 41:13 (7:3, 7:10, 24:0, 3:0)"], ["New England Patriots - Miami Dolphins", null, null, null, "Sunday, 14 Dec 2014, 17:00", "Final result 41:13 (7:3, 7:10, 24:0, 3:0)"], ["New England Patriots - Miami Dolphins", null, null, null, "Sunday, 14 Dec 2014, 17:00", "Final result 41:13 (7:3, 7:10, 24:0, 3:0)"], ["New England Patriots - Miami Dolphins", null, null, null, "Sunday, 14 Dec 2014, 17:00", "Final result 41:13 (7:3, 7:10, 24:0, 3:0)"], ["New England Patriots - Miami Dolphins", null, null, null, "Sunday, 14 Dec 2014, 17:00", "Final result 41:13 (7:3, 7:10, 24:0, 3:0)"], ["New England Patriots - Miami Dolphins", null, null, null, "Sunday, 14 Dec 2014, 17:00", "Final result 41:13 (7:3, 7:10, 24:0, 3:0)"], ["New England Patriots - Miami Dolphins", null, null, null, "Sunday, 14 Dec 2014, 17:00", "Final result 41:13 (7:3, 7:10, 24:0, 3:0)"], ["New England Patriots - Miami Dolphins", null, null, null, "Sunday, 14 Dec 2014, 17:00", "Final result 41:13 (7:3, 7:10, 24:0, 3:0)"], ["New England Patriots - Miami Dolphins", null, null, null, "Sunday, 14 Dec 2014, 17:00", "Final result 41:13 (7:3, 7:10, 24:0, 3:0)"], ["New England Patriots - Miami Dolphins", null, null, null, "Sunday, 14 Dec 2014, 17:00", "Final result 41:13 (7:3, 7:10, 24:0, 3:0)"], ["New England Patriots - Miami Dolphins", null, null, null, "Sunday, 14 Dec 2014, 17:00", "Final result 41:13 (7:3, 7:10, 24:0, 3:0)"], ["New England Patriots - Miami Dolphins", null, null, null, "Sunday, 14 Dec 2014, 17:00", "Final result 41:13 (7:3, 7:10, 24:0, 3:0)"], ["New England Patriots - Miami Dolphins", null, null, null, "Sunday, 14 Dec 2014, 17:00", "Final result 41:13 (7:3, 7:10, 24:0, 3:0)"], ["New England Patriots - Miami Dolphins", null, null, null, "Sunday, 14 Dec 2014, 17:00", "Final result 41:13 (7:3, 7:10, 24:0, 3:0)"], ["New England Patriots - Miami Dolphins", null, null, null, "Sunday, 14 Dec 2014, 17:00", "Final result 41:13 (7:3, 7:10, 24:0, 3:0)"], ["New England Patriots - Miami Dolphins", null, null, null, "Sunday, 14 Dec 2014, 17:00", "Final result 41:13 (7:3, 7:10, 24:0, 3:0)"], ["New England Patriots - Miami Dolphins", null, null, null, "Sunday, 14 Dec 2014, 17:00", "Final result 41:13 (7:3, 7:10, 24:0, 3:0)"], ["New England Patriots - Miami Dolphins", null, null, null, "Sunday, 14 Dec 2014, 17:00", "Final result 41:13 (7:3, 7:10, 24:0, 3:0)"], ["New England Patriots - Miami Dolphins", null, null, null, "Sunday, 14 Dec 2014, 17:00", "Final result 41:13 (7:3, 7:10, 24:0, 3:0)"], ["New England Patriots - Miami Dolphins", null, null, null, "Sunday, 14 Dec 2014, 17:00", "Final result 41:13 (7:3, 7:10, 24:0, 3:0)"], ["New England Patriots - Miami Dolphins", null, null, null, "Sunday, 14 Dec 2014, 17:00", "Final result 41:13 (7:3, 7:10, 24:0, 3:0)"], ["New York Giants - Washington Commanders", "bet-at-home", "-312", "+227", "Sunday, 14 Dec 2014, 17:00", "Final result 24:13 (7:3, 0:7, 10:3, 7:0)"], ["New York Giants - Washington Commanders", "bet365", "-286", "+229", "Sunday, 14 Dec 2014, 17:00", "Final result 24:13 (7:3, 0:7, 10:3, 7:0)"], ["New York Giants - Washington Commanders", "bwin", "-294", "+229", "Sunday, 14 Dec 2014, 17:00", "Final result 24:13 (7:3, 0:7, 10:3, 7:0)"], ["New York Giants - Washington Commanders", "Marathonbet", "-278", "+250", "Sunday, 14 Dec 2014, 17:00", "Final result 24:13 (7:3, 0:7, 10:3, 7:0)"], ["New York Giants - Washington Commanders", "Pinnacle", "-278", "+244", "Sunday, 14 Dec 2014, 17:00", "Final result 24:13 (7:3, 0:7, 10:3, 7:0)"], ["New York Giants - Washington Commanders", "Unibet", "-286", "+229", "Sunday, 14 Dec 2014, 17:00", "Final result 24:13 (7:3, 0:7, 10:3, 7:0)"], ["New York Giants - Washington Commanders", "William Hill", "-278", "+240", "Sunday, 14 Dec 2014, 17:00", "Final result 24:13 (7:3, 0:7, 10:3, 7:0)"], ["New York Giants - Washington Commanders", null, null, null, "Sunday, 14 Dec 2014, 17:00", "Final result 24:13 (7:3, 0:7, 10:3, 7:0)"], ["New York Giants - Washington Commanders", null, null, null, "Sunday, 14 Dec 2014, 17:00", "Final result 24:13 (7:3, 0:7, 10:3, 7:0)"], ["New York Giants - Washington Commanders", null, null, null, "Sunday, 14 Dec 2014, 17:00", "Final result 24:13 (7:3, 0:7, 10:3, 7:0)"], ["New York Giants - Washington Commanders", null, null, null, "Sunday, 14 Dec 2014, 17:00", "Final result 24:13 (7:3, 0:7, 10:3, 7:0)"], ["New York Giants - Washington Commanders", null, null, null, "Sunday, 14 Dec 2014, 17:00", "Final result 24:13 (7:3, 0:7, 10:3, 7:0)"], ["New York Giants - Washington Commanders", null, null, null, "Sunday, 14 Dec 2014, 17:00", "Final result 24:13 (7:3, 0:7, 10:3, 7:0)"], ["New York Giants - Washington Commanders", null, null, null, "Sunday, 14 Dec 2014, 17:00", "Final result 24:13 (7:3, 0:7, 10:3, 7:0)"], ["New York Giants - Washington Commanders", null, null, null, "Sunday, 14 Dec 2014, 17:00", "Final result 24:13 (7:3, 0:7, 10:3, 7:0)"], ["New York Giants - Washington Commanders", null, null, null, "Sunday, 14 Dec 2014, 17:00", "Final result 24:13 (7:3, 0:7, 10:3, 7:0)"], ["New York Giants - Washington Commanders", null, null, null, "Sunday, 14 Dec 2014, 17:00", "Final result 24:13 (7:3, 0:7, 10:3, 7:0)"], ["New York Giants - Washington Commanders", null, null, null, "Sunday, 14 Dec 2014, 17:00", "Final result 24:13 (7:3, 0:7, 10:3, 7:0)"], ["New York Giants - Washington Commanders", null, null, null, "Sunday, 14 Dec 2014, 17:00", "Final result 24:13 (7:3, 0:7, 10:3, 7:0)"], ["New York Giants - Washington Commanders", null, null, null, "Sunday, 14 Dec 2014, 17:00", "Final result 24:13 (7:3, 0:7, 10:3, 7:0)"], ["New York Giants - Washington Commanders", null, null, null, "Sunday, 14 Dec 2014, 17:00", "Final result 24:13 (7:3, 0:7, 10:3, 7:0)"], ["New York Giants - Washington Commanders", null, null, null, "Sunday, 14 Dec 2014, 17:00", "Final result 24:13 (7:3, 0:7, 10:3, 7:0)"], ["New York Giants - Washington Commanders", null, null, null, "Sunday, 14 Dec 2014, 17:00", "Final result 24:13 (7:3, 0:7, 10:3, 7:0)"], ["New York Giants - Washington Commanders", null, null, null, "Sunday, 14 Dec 2014, 17:00", "Final result 24:13 (7:3, 0:7, 10:3, 7:0)"], ["New York Giants - Washington Commanders", null, null, null, "Sunday, 14 Dec 2014, 17:00", "Final result 24:13 (7:3, 0:7, 10:3, 7:0)"], ["New York Giants - Washington Commanders", null, null, null, "Sunday, 14 Dec 2014, 17:00", "Final result 24:13 (7:3, 0:7, 10:3, 7:0)"], ["New York Giants - Washington Commanders", null, null, null, "Sunday, 14 Dec 2014, 17:00", "Final result 24:13 (7:3, 0:7, 10:3, 7:0)"], ["New York Giants - Washington Commanders", null, null, null, "Sunday, 14 Dec 2014, 17:00", "Final result 24:13 (7:3, 0:7, 10:3, 7:0)"], ["New York Giants - Washington Commanders", null, null, null, "Sunday, 14 Dec 2014, 17:00", "Final result 24:13 (7:3, 0:7, 10:3, 7:0)"]]}